topsis/__init__.py
topsis/topsis.py
topsis_swikriti_102303440-0.0.1.dist-info/METADATA
topsis_swikriti_102303440-0.0.1.dist-info/WHEEL
topsis_swikriti_102303440-0.0.1.dist-info/entry_points.txt
topsis_swikriti_102303440-0.0.1.dist-info/top_level.txt
topsis_swikriti_102303440-0.0.1.dist-info/RECORD
