Metadata-Version: 2.4
Name: Topsis-Swikriti-102303440
Version: 0.0.1
Summary: A Python package for TOPSIS method
Author: Swikriti
Author-email: srathore_be23@thapar.edu
Requires-Dist: pandas
Requires-Dist: numpy
Dynamic: author
Dynamic: author-email
Dynamic: requires-dist
Dynamic: summary
